langvision/__init__.py
langvision/auth.py
langvision/example.py
langvision/facade.py
langvision/model_zoo.py
langvision/agents/__init__.py
langvision/api/__init__.py
langvision/api/client.py
langvision/api/cloud.py
langvision/callbacks/__init__.py
langvision/callbacks/base.py
langvision/callbacks/early_stopping.py
langvision/callbacks/logging.py
langvision/callbacks/registry.py
langvision/cli/__init__.py
langvision/cli/auth.py
langvision/cli/complete_cli.py
langvision/cli/config.py
langvision/cli/evaluate.py
langvision/cli/export.py
langvision/cli/finetune.py
langvision/cli/model_zoo.py
langvision/cli/rich_help.py
langvision/cli/train.py
langvision/cli/utils.py
langvision/components/__init__.py
langvision/components/attention.py
langvision/components/mlp.py
langvision/components/patch_embedding.py
langvision/concepts/__init__.py
langvision/concepts/ccot.py
langvision/concepts/cot.py
langvision/concepts/dpo.py
langvision/concepts/grpo.py
langvision/concepts/lime.py
langvision/concepts/ppo.py
langvision/concepts/rlhf.py
langvision/concepts/rlvr.py
langvision/concepts/shap.py
langvision/config/__init__.py
langvision/data/__init__.py
langvision/data/datasets.py
langvision/data/enhanced_datasets.py
langvision/data/preprocessing.py
langvision/evaluation/__init__.py
langvision/export/__init__.py
langvision/filesystem/__init__.py
langvision/inference/__init__.py
langvision/llm/__init__.py
langvision/memory/__init__.py
langvision/models/__init__.py
langvision/models/lora.py
langvision/models/model_loader.py
langvision/models/multimodal.py
langvision/models/resnet.py
langvision/models/vision_transformer.py
langvision/sync/__init__.py
langvision/telemetry/__init__.py
langvision/training/__init__.py
langvision/training/acceleration.py
langvision/training/advanced_trainer.py
langvision/training/config.py
langvision/training/fast_attention.py
langvision/training/fast_lora.py
langvision/training/fast_trainer.py
langvision/training/finetuner.py
langvision-0.1.51.dist-info/METADATA
langvision-0.1.51.dist-info/WHEEL
langvision-0.1.51.dist-info/entry_points.txt
langvision-0.1.51.dist-info/top_level.txt
langvision-0.1.51.dist-info/RECORD
