Metadata-Version: 2.4
Name: langvision
Version: 0.1.51
Summary: Efficient LoRA Fine-Tuning for Vision LLMs with advanced CLI and model zoo
Author-email: Pritesh Raj <priteshraj10@gmail.com>
Maintainer-email: Pritesh Raj <priteshraj10@gmail.com>
License-Expression: MIT
Project-URL: Homepage, https://github.com/langtrain-ai/langvision
Project-URL: Documentation, https://github.com/langtrain-ai/langvision/tree/main/docs
Project-URL: Repository, https://github.com/langtrain-ai/langvision
Project-URL: Bug Tracker, https://github.com/langtrain-ai/langvision/issues
Project-URL: Source Code, https://github.com/langtrain-ai/langvision
Project-URL: Changelog, https://github.com/langtrain-ai/langvision/blob/main/CHANGELOG.md
Keywords: vision,transformer,lora,fine-tuning,deep-learning,computer-vision
Classifier: Development Status :: 4 - Beta
Classifier: Intended Audience :: Developers
Classifier: Intended Audience :: Science/Research
Classifier: Operating System :: OS Independent
Classifier: Programming Language :: Python :: 3
Classifier: Programming Language :: Python :: 3.8
Classifier: Programming Language :: Python :: 3.9
Classifier: Programming Language :: Python :: 3.10
Classifier: Programming Language :: Python :: 3.11
Classifier: Programming Language :: Python :: 3.12
Classifier: Topic :: Scientific/Engineering :: Artificial Intelligence
Classifier: Topic :: Software Development :: Libraries :: Python Modules
Classifier: Topic :: Scientific/Engineering :: Image Processing
Requires-Python: >=3.8
Requires-Dist: torch>=1.10.0
Requires-Dist: torchvision>=0.11.0
Requires-Dist: numpy>=1.21.0
Requires-Dist: tqdm>=4.62.0
Requires-Dist: pyyaml>=6.0
Requires-Dist: scipy>=1.7.0
Requires-Dist: matplotlib>=3.5.0
Requires-Dist: pillow>=8.3.0
Requires-Dist: timm>=0.6.0
Requires-Dist: transformers>=4.20.0
Requires-Dist: toml>=0.10.0
Requires-Dist: scikit-learn>=1.0.0
Requires-Dist: pandas>=1.3.0
Requires-Dist: opencv-python-headless>=4.5.0
Requires-Dist: wandb>=0.13.0
Requires-Dist: rich>=13.0.0
Provides-Extra: dev
Requires-Dist: pytest>=7.0.0; extra == "dev"
Requires-Dist: pytest-cov>=4.0.0; extra == "dev"
Requires-Dist: pytest-mock>=3.8.0; extra == "dev"
Requires-Dist: black>=22.0.0; extra == "dev"
Requires-Dist: isort>=5.10.0; extra == "dev"
Requires-Dist: flake8>=5.0.0; extra == "dev"
Requires-Dist: mypy>=1.0.0; extra == "dev"
Requires-Dist: pre-commit>=2.20.0; extra == "dev"
Requires-Dist: bandit>=1.7.0; extra == "dev"
Provides-Extra: docs
Requires-Dist: sphinx>=5.0.0; extra == "docs"
Requires-Dist: sphinx-rtd-theme>=1.0.0; extra == "docs"
Requires-Dist: myst-parser>=0.18.0; extra == "docs"
Requires-Dist: sphinx-autodoc-typehints>=1.19.0; extra == "docs"
Provides-Extra: examples
Requires-Dist: jupyter>=1.0.0; extra == "examples"
Requires-Dist: ipywidgets>=7.6.0; extra == "examples"
Requires-Dist: tensorboard>=2.9.0; extra == "examples"
Requires-Dist: wandb>=0.13.0; extra == "examples"
Provides-Extra: gpu
Requires-Dist: torch>=1.10.0; extra == "gpu"
Requires-Dist: torchvision>=0.11.0; extra == "gpu"
